sweetpareto/__init__.py
sweetpareto/_engines.py
sweetpareto/_front.py
sweetpareto/_sns.py
sweetpareto/types.py
sweetpareto/vis.py
sweetpareto-1.0.0rc0.dist-info/METADATA
sweetpareto-1.0.0rc0.dist-info/WHEEL
sweetpareto-1.0.0rc0.dist-info/licenses/LICENSE
sweetpareto-1.0.0rc0.dist-info/RECORD
