Metadata-Version: 2.4
Name: sweetpareto
Version: 1.0.0rc0
Summary: Extracting and plotting pareto fronts
Project-URL: Homepage, https://codeberg.org/djsn/sweet-pareto
Project-URL: Issues, https://codeberg.org/djsn/sweet-pareto/issues
Maintainer-email: Andrew Johnson <drew@djsn.dev>
License-Expression: MPL-2.0
License-File: LICENSE
Classifier: Development Status :: 3 - Alpha
Classifier: Intended Audience :: Science/Research
Classifier: License :: OSI Approved :: Mozilla Public License 2.0 (MPL 2.0)
Classifier: Natural Language :: English
Classifier: Programming Language :: Python
Classifier: Programming Language :: Python :: 3.13
Requires-Python: >=3.13
Requires-Dist: numpy
Requires-Dist: pandas
Provides-Extra: plot
Requires-Dist: seaborn<0.14.0,>=0.12.0; extra == 'plot'
